iris_client/__init__.py
iris_client/client.py
iris_client/constants.py
iris_client/logger.py
iris_client/py.typed
dioptra_iris_client-0.5.3.dist-info/METADATA
dioptra_iris_client-0.5.3.dist-info/WHEEL
dioptra_iris_client-0.5.3.dist-info/licenses/LICENSE
dioptra_iris_client-0.5.3.dist-info/RECORD
